{
  "code": "1",
  "message": "successful",
  "action": null,
  "data": {
    "id": 1,
    "ref": "120-910-45",
    "customer": {
      "name": "John Doe",
      "id": "C12345",
      "phone": "+1234567890",
      "email": "johndoe@example.com",
      "address": "Dubai, JVC"
    },
    "vendor": {
      "name": "John Doe",
      "id": "C12345",
      "phone": "+1234567890",
      "email": "johndoe@example.com",
      "company": "Company"
    },
    "car": {
      "make": "Nissan",
      "model": "Altima",
      "color": "Red",
      "license_plate": "XYZ123",
      "vin_number": "SV3001692664F8OW"
    },
    "status": "awaiting_pickup",
    "type": "drop_off",
    "source_location": {
      "lat": 25.25998298797378,
      "long": 55.3325171957663,
      "address_notes": "AWR Head Office"
    },
    "destination_location": {
      "lat": 25.199429016702688,
      "long": 55.27507425522772,
      "address_notes": "Dubai Mall"
    }
  }
}
